MANIFEST.in
README.txt
setup.py
XStatic_BootstrapTags.egg-info/PKG-INFO
XStatic_BootstrapTags.egg-info/SOURCES.txt
XStatic_BootstrapTags.egg-info/dependency_links.txt
XStatic_BootstrapTags.egg-info/namespace_packages.txt
XStatic_BootstrapTags.egg-info/not-zip-safe
XStatic_BootstrapTags.egg-info/top_level.txt
xstatic/__init__.py
xstatic/pkg/__init__.py
xstatic/pkg/bootstrapinput/__init__.py
xstatic/pkg/bootstrapinput/data/bootstrap-tagsinput.css
xstatic/pkg/bootstrapinput/data/bootstrap-tagsinput.js