Metadata-Version: 1.0
Name: XStatic-BootstrapTags
Version: 1.10.2.1
Summary: BootstrapTags 1.10.2 (XStatic packaging standard)
Home-page: http://timschlechter.github.io/bootstrap-tagsinput/examples/
Author: Yask Srivastava
Author-email: yask123@gmail.com
License: (same as BootstrapTags)
Keywords: bootstrapinput xstatic
Platform: any
